better_imap/__init__.py
better_imap/errors.py
better_imap/imap.py
better_imap/mailbox.py
better_imap/models.py
better_imap/services.py
better_imap/utils.py
better_imap-1.4.8.dist-info/METADATA
better_imap-1.4.8.dist-info/WHEEL
better_imap-1.4.8.dist-info/licenses/LICENCE
better_imap-1.4.8.dist-info/RECORD
