Metadata-Version: 2.4
Name: better-imap
Version: 1.4.8
Summary: IMAP tools
License-File: LICENCE
Author: T1murKO
Requires-Python: >=3.11,<3.14
Classifier: Programming Language :: Python :: 3
Classifier: Programming Language :: Python :: 3.11
Classifier: Programming Language :: Python :: 3.12
Classifier: Programming Language :: Python :: 3.13
Requires-Dist: aioimaplib (>=2.0.1,<2.1)
Requires-Dist: async-timeout (>=4.0,<5.0)
Requires-Dist: beautifulsoup4 (>=4.12,<5.0)
Requires-Dist: better-proxy (>=1.1,<2.0)
Requires-Dist: html2text (>=2024.2.26,<2025.0.0)
Requires-Dist: python-socks (>=2.5,<3.0)
Requires-Dist: pytz (>=2025.1,<2026.0)
Requires-Dist: tenacity (>=9.0.0,<10)
